app/__init__.py
app/api/__init__.py
app/api/health.py
app/api/servers.py
app/core/__init__.py
app/core/config.py
app/models/__init__.py
app/models/mcp_config.py
app/services/__init__.py
app/services/config_service.py
app/services/mcp_factory.py
app/services/server_manager.py
jewei_mcpcat-0.1.1.dist-info/METADATA
jewei_mcpcat-0.1.1.dist-info/WHEEL
jewei_mcpcat-0.1.1.dist-info/entry_points.txt
jewei_mcpcat-0.1.1.dist-info/RECORD
