Metadata-Version: 2.4
Name: jewei-mcpcat
Version: 0.1.1
Summary: MCP聚合平台 - 支持多种MCP协议的统一管理平台
Author-email: MCPCat Team <team@mcpcat.com>
Requires-Python: >=3.10
Requires-Dist: aiofiles>=24.1.0
Requires-Dist: fastapi>=0.115.0
Requires-Dist: fastmcp>=2.8.1
Requires-Dist: httpx>=0.24.0
Requires-Dist: pydantic>=2.10.0
Requires-Dist: python-dotenv>=1.0.1
Requires-Dist: python-multipart>=0.0.12
Requires-Dist: requests>=2.32.0
Requires-Dist: uvicorn[standard]>=0.32.0
Provides-Extra: dev
Requires-Dist: black>=23.0.0; extra == 'dev'
Requires-Dist: flake8>=6.0.0; extra == 'dev'
Requires-Dist: isort>=5.12.0; extra == 'dev'
Requires-Dist: pytest-asyncio>=0.21.0; extra == 'dev'
Requires-Dist: pytest>=7.0.0; extra == 'dev'
